nion/data/Calibration.py
nion/data/Core.py
nion/data/DataAndMetadata.py
nion/data/Image.py
nion/data/MultiDimensionalProcessing.py
nion/data/RGB.py
nion/data/TemplateMatching.py
nion/data/__init__.py
nion/data/py.typed
nion/data/xdata_1_0.py
nion/data/test/Calibration_test.py
nion/data/test/Core_test.py
nion/data/test/ExtendedData_test.py
nion/data/test/Image_test.py
nion/data/test/MultiDimensionalProcessing_test.py
nion/data/test/__init__.py
niondata-15.9.1.dist-info/licenses/LICENSE.txt
niondata-15.9.1.dist-info/METADATA
niondata-15.9.1.dist-info/WHEEL
niondata-15.9.1.dist-info/top_level.txt
niondata-15.9.1.dist-info/RECORD
