Metadata-Version: 2.4
Name: niondata
Version: 15.9.1
Summary: A data processing library for Nion Swift.
Home-page: https://github.com/nion-software/niondata
Author: Nion Software
Author-email: swift@nion.com
License: Apache-2.0
Classifier: Development Status :: 5 - Production/Stable
Classifier: License :: OSI Approved :: Apache Software License
Classifier: Programming Language :: Python :: 3.11
Classifier: Programming Language :: Python :: 3.12
Classifier: Programming Language :: Python :: 3.13
Requires-Python: >=3.11
License-File: LICENSE.txt
Requires-Dist: numpy<3.0,>=2.0
Requires-Dist: scipy
Requires-Dist: nionutils<5.0.0,>=4.14.0
Dynamic: license-file
